pybel_artifactory/__init__.py
pybel_artifactory/__main__.py
pybel_artifactory/cli.py
pybel_artifactory/constants.py
pybel_artifactory/defaults.py
pybel_artifactory/deploy.py
pybel_artifactory/hashing.py
pybel_artifactory/history.py
pybel_artifactory/latest.py
pybel_artifactory/today.py
pybel_artifactory/utils.py
pybel_artifactory-0.0.2.dist-info/LICENSE.txt
pybel_artifactory-0.0.2.dist-info/METADATA
pybel_artifactory-0.0.2.dist-info/RECORD
pybel_artifactory-0.0.2.dist-info/WHEEL
pybel_artifactory-0.0.2.dist-info/entry_points.txt
pybel_artifactory-0.0.2.dist-info/top_level.txt
