Metadata-Version: 2.1
Name: pybel-artifactory
Version: 0.0.2
Summary: A PyBEL extension for handling BEL resources with Artifactory
Home-page: https://github.com/pybel/pybel-artifactory
Author: Charles Tapley Hoyt
Author-email: charles.hoyt@scai.fraunhofer.de
Maintainer: Charles Tapley Hoyt
Maintainer-email: charles.hoyt@scai.fraunhofer.de
License: MIT License
Keywords: Biological Expression Language,BEL,Systems Biology,Networks Biology
Platform: UNKNOWN
Classifier: Development Status :: 4 - Beta
Classifier: Environment :: Console
Classifier: Intended Audience :: Developers
Classifier: Intended Audience :: Science/Research
Classifier: License :: OSI Approved :: MIT License
Classifier: Operating System :: OS Independent
Classifier: Programming Language :: Python
Classifier: Programming Language :: Python :: 2.7
Classifier: Programming Language :: Python :: 3.4
Classifier: Programming Language :: Python :: 3.5
Classifier: Programming Language :: Python :: 3.6
Classifier: Topic :: Scientific/Engineering :: Bio-Informatics
Requires-Dist: pybel
Requires-Dist: artifactory
